django_simpletask2_server.py
django_simpletask2_server-0.1.1.dist-info/LICENSE
django_simpletask2_server-0.1.1.dist-info/METADATA
django_simpletask2_server-0.1.1.dist-info/WHEEL
django_simpletask2_server-0.1.1.dist-info/entry_points.txt
django_simpletask2_server-0.1.1.dist-info/top_level.txt
django_simpletask2_server-0.1.1.dist-info/RECORD
