Metadata-Version: 2.1
Name: django-simpletask2-server
Version: 0.1.1
Summary: Django simpletask2 handler server.
Home-page: UNKNOWN
Author: Yang BangJiang
Maintainer: Yang BangJiang
License: MIT
Keywords: django-simpletask2
Platform: UNKNOWN
Classifier: Development Status :: 5 - Production/Stable
Classifier: Intended Audience :: Developers
Classifier: Topic :: Software Development :: Libraries :: Python Modules
Classifier: License :: OSI Approved :: MIT License
Classifier: Programming Language :: Python :: 3
Classifier: Programming Language :: Python :: 3 :: Only
License-File: LICENSE
Requires-Dist: daemon-application >=0.5.2
Requires-Dist: fastutils >=0.39.1
Requires-Dist: requests
Requires-Dist: click
Requires-Dist: redis
